{
  "AD": 101,
  "AE": 125,
  "AF": 5,
  "AG": 97,
  "AL": 75,
  "AM": 36,
  "AO": 26,
  "AR": 106,
  "AT": 119,
  "AU": 109,
  "AZ": 35,
  "BA": 72,
  "BB": 103,
  "BD": 19,
  "BE": 123,
  "BF": 28,
  "BG": 117,
  "BH": 46,
  "BI": 20,
  "BJ": 38,
  "BN": 103,
  "BO": 35,
  "BR": 111,
  "BS": 103,
  "BT": 19,
  "BW": 44,
  "BY": 43,
  "BZ": 56,
  "CD": 20,
  "CF": 22,
  "CG": 22,
  "CH": 120,
  "CI": 31,
  "CL": 106,
  "CM": 22,
  "CN": 55,
  "CO": 85,
  "CR": 92,
  "CU": 27,
  "CV": 35,
  "CY": 121,
  "CZ": 119,
  "DE": 120,
  "DJ": 12,
  "DK": 120,
  "DM": 92,
  "DO": 37,
  "DZ": 23,
  "EC": 50,
  "EE": 112,
  "EG": 21,
  "ER": 11,
  "ES": 121,
  "ET": 14,
  "FI": 124,
  "FJ": 45,
  "FM": 67,
  "FR": 122,
  "GA": 29,
  "GB": 117,
  "GD": 91,
  "GE": 84,
  "GH": 45,
  "GM": 44,
  "GN": 28,
  "GQ": 19,
  "GR": 118,
  "GT": 77,
  "GW": 27,
  "GY": 45,
  "HK": 135,
  "HN": 77,
  "HR": 114,
  "HT": 13,
  "HU": 117,
  "ID": 45,
  "IE": 121,
  "IL": 100,
  "IN": 26,
  "IQ": 13,
  "IR": 17,
  "IS": 112,
  "IT": 119,
  "JM": 52,
  "JO": 24,
  "JP": 113,
  "KE": 38,
  "KG": 28,
  "KH": 23,
  "KI": 76,
  "KM": 19,
  "KN": 100,
  "KP": 10,
  "KR": 116,
  "KW": 59,
  "KZ": 46,
  "LA": 22,
  "LB": 19,
  "LC": 84,
  "LI": 106,
  "LK": 18,
  "LR": 24,
  "LS": 41,
  "LT": 115,
  "LU": 120,
  "LV": 113,
  "LY": 15,
  "MA": 43,
  "MC": 103,
  "MD": 76,
  "ME": 79,
  "MG": 28,
  "MH": 73,
  "ML": 28,
  "MM": 17,
  "MN": 34,
  "MO": 98,
  "MR": 26,
  "MT": 120,
  "MU": 92,
  "MV": 56,
  "MW": 38,
  "MX": 97,
  "MY": 127,
  "MZ": 32,
  "NA": 44,
  "NE": 31,
  "NG": 27,
  "NI": 70,
  "NL": 123,
  "NO": 120,
  "NP": 11,
  "NR": 40,
  "NZ": 111,
  "OM": 47,
  "PA": 85,
  "PE": 91,
  "PG": 37,
  "PH": 37,
  "PK": 12,
  "PL": 118,
  "PS": 13,
  "PT": 119,
  "PW": 63,
  "PY": 86,
  "QA": 68,
  "RO": 118,
  "RS": 87,
  "RU": 81,
  "RW": 28,
  "SA": 53,
  "SB": 83,
  "SC": 102,
  "SD": 16,
  "SE": 122,
  "SG": 132,
  "SI": 117,
  "SK": 116,
  "SL": 41,
  "SM": 102,
  "SN": 34,
  "SO": 12,
  "SR": 38,
  "SS": 19,
  "ST": 24,
  "SV": 79,
  "SY": 7,
  "SZ": 38,
  "TD": 26,
  "TG": 30,
  "TH": 39,
  "TJ": 25,
  "TL": 58,
  "TM": 16,
  "TN": 36,
  "TO": 78,
  "TR": 73,
  "TT": 94,
  "TV": 80,
  "TW": 72,
  "TZ": 43,
  "UA": 91,
  "UG": 34,
  "US": 111,
  "UY": 98,
  "UZ": 33,
  "VA": 93,
  "VC": 96,
  "VE": 71,
  "VN": 26,
  "VU": 43,
  "WS": 82,
  "XK": 52,
  "YE": 7,
  "ZA": 61,
  "ZM": 40,
  "ZW": 35
}